{
  "type": "File",
  "start": 0,
  "end": 305,
  "loc": {
    "start": {
      "line": 1,
      "column": 0
    },
    "end": {
      "line": 14,
      "column": 0
    }
  },
  "program": {
    "type": "Program",
    "start": 0,
    "end": 305,
    "loc": {
      "start": {
        "line": 1,
        "column": 0
      },
      "end": {
        "line": 14,
        "column": 0
      }
    },
    "sourceType": "module",
    "body": [
      {
        "type": "Identifier",
        "start": 13,
        "end": 264,
        "loc": {
          "start": {
            "line": 2,
            "column": 0
          },
          "end": {
            "line": 11,
            "column": 2
          }
        },
        "declarations": [
          {
            "type": "VariableDeclarator",
            "start": 19,
            "end": 263,
            "loc": {
              "start": {
                "line": 2,
                "column": 6
              },
              "end": {
                "line": 11,
                "column": 1
              }
            },
            "id": {
              "type": "Identifier",
              "start": 19,
              "end": 41,
              "loc": {
                "start": {
                  "line": 2,
                  "column": 6
                },
                "end": {
                  "line": 2,
                  "column": 28
                },
                "identifierName": "eventEmitterMiddleware"
              },
              "name": "eventEmitterMiddleware",
              "leadingComments": null
            },
            "init": {
              "type": "ArrowFunctionExpression",
              "start": 44,
              "end": 263,
              "loc": {
                "start": {
                  "line": 2,
                  "column": 31
                },
                "end": {
                  "line": 11,
                  "column": 1
                }
              },
              "id": null,
              "generator": false,
              "expression": true,
              "async": false,
              "params": [
                {
                  "type": "Identifier",
                  "start": 44,
                  "end": 49,
                  "loc": {
                    "start": {
                      "line": 2,
                      "column": 31
                    },
                    "end": {
                      "line": 2,
                      "column": 36
                    },
                    "identifierName": "store"
                  },
                  "name": "store"
                }
              ],
              "body": {
                "type": "ArrowFunctionExpression",
                "start": 53,
                "end": 263,
                "loc": {
                  "start": {
                    "line": 2,
                    "column": 40
                  },
                  "end": {
                    "line": 11,
                    "column": 1
                  }
                },
                "id": null,
                "generator": false,
                "expression": true,
                "async": false,
                "params": [
                  {
                    "type": "Identifier",
                    "start": 53,
                    "end": 57,
                    "loc": {
                      "start": {
                        "line": 2,
                        "column": 40
                      },
                      "end": {
                        "line": 2,
                        "column": 44
                      },
                      "identifierName": "next"
                    },
                    "name": "next"
                  }
                ],
                "body": {
                  "type": "ArrowFunctionExpression",
                  "start": 61,
                  "end": 263,
                  "loc": {
                    "start": {
                      "line": 2,
                      "column": 48
                    },
                    "end": {
                      "line": 11,
                      "column": 1
                    }
                  },
                  "id": null,
                  "generator": false,
                  "expression": false,
                  "async": false,
                  "params": [
                    {
                      "type": "Identifier",
                      "start": 61,
                      "end": 67,
                      "loc": {
                        "start": {
                          "line": 2,
                          "column": 48
                        },
                        "end": {
                          "line": 2,
                          "column": 54
                        },
                        "identifierName": "action"
                      },
                      "name": "action"
                    }
                  ],
                  "body": {
                    "type": "BlockStatement",
                    "start": 71,
                    "end": 263,
                    "loc": {
                      "start": {
                        "line": 2,
                        "column": 58
                      },
                      "end": {
                        "line": 11,
                        "column": 1
                      }
                    },
                    "body": [
                      {
                        "type": "VariableDeclaration",
                        "start": 77,
                        "end": 202,
                        "loc": {
                          "start": {
                            "line": 3,
                            "column": 4
                          },
                          "end": {
                            "line": 7,
                            "column": 7
                          }
                        },
                        "declarations": [
                          {
                            "type": "VariableDeclarator",
                            "start": 83,
                            "end": 201,
                            "loc": {
                              "start": {
                                "line": 3,
                                "column": 10
                              },
                              "end": {
                                "line": 7,
                                "column": 6
                              }
                            },
                            "id": {
                              "type": "Identifier",
                              "start": 83,
                              "end": 88,
                              "loc": {
                                "start": {
                                  "line": 3,
                                  "column": 10
                                },
                                "end": {
                                  "line": 3,
                                  "column": 15
                                },
                                "identifierName": "event"
                              },
                              "name": "event"
                            },
                            "init": {
                              "type": "NewExpression",
                              "start": 91,
                              "end": 201,
                              "loc": {
                                "start": {
                                  "line": 3,
                                  "column": 18
                                },
                                "end": {
                                  "line": 7,
                                  "column": 6
                                }
                              },
                              "callee": {
                                "type": "Identifier",
                                "start": 95,
                                "end": 106,
                                "loc": {
                                  "start": {
                                    "line": 3,
                                    "column": 22
                                  },
                                  "end": {
                                    "line": 3,
                                    "column": 33
                                  },
                                  "identifierName": "CustomEvent"
                                },
                                "name": "CustomEvent"
                              },
                              "arguments": [
                                {
                                  "type": "TemplateLiteral",
                                  "start": 107,
                                  "end": 127,
                                  "loc": {
                                    "start": {
                                      "line": 3,
                                      "column": 34
                                    },
                                    "end": {
                                      "line": 3,
                                      "column": 54
                                    }
                                  },
                                  "expressions": [
                                    {
                                      "type": "MemberExpression",
                                      "start": 114,
                                      "end": 125,
                                      "loc": {
                                        "start": {
                                          "line": 3,
                                          "column": 41
                                        },
                                        "end": {
                                          "line": 3,
                                          "column": 52
                                        }
                                      },
                                      "object": {
                                        "type": "Identifier",
                                        "start": 114,
                                        "end": 120,
                                        "loc": {
                                          "start": {
                                            "line": 3,
                                            "column": 41
                                          },
                                          "end": {
                                            "line": 3,
                                            "column": 47
                                          },
                                          "identifierName": "action"
                                        },
                                        "name": "action"
                                      },
                                      "property": {
                                        "type": "Identifier",
                                        "start": 121,
                                        "end": 125,
                                        "loc": {
                                          "start": {
                                            "line": 3,
                                            "column": 48
                                          },
                                          "end": {
                                            "line": 3,
                                            "column": 52
                                          },
                                          "identifierName": "type"
                                        },
                                        "name": "type"
                                      },
                                      "computed": false
                                    }
                                  ],
                                  "quasis": [
                                    {
                                      "type": "TemplateElement",
                                      "start": 108,
                                      "end": 112,
                                      "loc": {
                                        "start": {
                                          "line": 3,
                                          "column": 35
                                        },
                                        "end": {
                                          "line": 3,
                                          "column": 39
                                        }
                                      },
                                      "value": {
                                        "raw": "rwc-",
                                        "cooked": "rwc-"
                                      },
                                      "tail": false
                                    },
                                    {
                                      "type": "TemplateElement",
                                      "start": 126,
                                      "end": 126,
                                      "loc": {
                                        "start": {
                                          "line": 3,
                                          "column": 53
                                        },
                                        "end": {
                                          "line": 3,
                                          "column": 53
                                        }
                                      },
                                      "value": {
                                        "raw": "",
                                        "cooked": ""
                                      },
                                      "tail": true
                                    }
                                  ]
                                },
                                {
                                  "type": "ObjectExpression",
                                  "start": 129,
                                  "end": 200,
                                  "loc": {
                                    "start": {
                                      "line": 3,
                                      "column": 56
                                    },
                                    "end": {
                                      "line": 7,
                                      "column": 5
                                    }
                                  },
                                  "properties": [
                                    {
                                      "type": "ObjectProperty",
                                      "start": 139,
                                      "end": 194,
                                      "loc": {
                                        "start": {
                                          "line": 4,
                                          "column": 8
                                        },
                                        "end": {
                                          "line": 6,
                                          "column": 9
                                        }
                                      },
                                      "method": false,
                                      "shorthand": false,
                                      "computed": false,
                                      "key": {
                                        "type": "Identifier",
                                        "start": 139,
                                        "end": 145,
                                        "loc": {
                                          "start": {
                                            "line": 4,
                                            "column": 8
                                          },
                                          "end": {
                                            "line": 4,
                                            "column": 14
                                          },
                                          "identifierName": "detail"
                                        },
                                        "name": "detail"
                                      },
                                      "value": {
                                        "type": "ObjectExpression",
                                        "start": 147,
                                        "end": 194,
                                        "loc": {
                                          "start": {
                                            "line": 4,
                                            "column": 16
                                          },
                                          "end": {
                                            "line": 6,
                                            "column": 9
                                          }
                                        },
                                        "properties": [
                                          {
                                            "type": "ObjectProperty",
                                            "start": 161,
                                            "end": 184,
                                            "loc": {
                                              "start": {
                                                "line": 5,
                                                "column": 12
                                              },
                                              "end": {
                                                "line": 5,
                                                "column": 35
                                              }
                                            },
                                            "method": false,
                                            "shorthand": false,
                                            "computed": false,
                                            "key": {
                                              "type": "Identifier",
                                              "start": 161,
                                              "end": 168,
                                              "loc": {
                                                "start": {
                                                  "line": 5,
                                                  "column": 12
                                                },
                                                "end": {
                                                  "line": 5,
                                                  "column": 19
                                                },
                                                "identifierName": "payload"
                                              },
                                              "name": "payload"
                                            },
                                            "value": {
                                              "type": "MemberExpression",
                                              "start": 170,
                                              "end": 184,
                                              "loc": {
                                                "start": {
                                                  "line": 5,
                                                  "column": 21
                                                },
                                                "end": {
                                                  "line": 5,
                                                  "column": 35
                                                }
                                              },
                                              "object": {
                                                "type": "Identifier",
                                                "start": 170,
                                                "end": 176,
                                                "loc": {
                                                  "start": {
                                                    "line": 5,
                                                    "column": 21
                                                  },
                                                  "end": {
                                                    "line": 5,
                                                    "column": 27
                                                  },
                                                  "identifierName": "action"
                                                },
                                                "name": "action"
                                              },
                                              "property": {
                                                "type": "Identifier",
                                                "start": 177,
                                                "end": 184,
                                                "loc": {
                                                  "start": {
                                                    "line": 5,
                                                    "column": 28
                                                  },
                                                  "end": {
                                                    "line": 5,
                                                    "column": 35
                                                  },
                                                  "identifierName": "payload"
                                                },
                                                "name": "payload"
                                              },
                                              "computed": false
                                            }
                                          }
                                        ]
                                      }
                                    }
                                  ]
                                }
                              ]
                            }
                          }
                        ],
                        "kind": "const"
                      },
                      {
                        "type": "ExpressionStatement",
                        "start": 208,
                        "end": 236,
                        "loc": {
                          "start": {
                            "line": 9,
                            "column": 4
                          },
                          "end": {
                            "line": 9,
                            "column": 32
                          }
                        },
                        "expression": {
                          "type": "CallExpression",
                          "start": 208,
                          "end": 235,
                          "loc": {
                            "start": {
                              "line": 9,
                              "column": 4
                            },
                            "end": {
                              "line": 9,
                              "column": 31
                            }
                          },
                          "callee": {
                            "type": "MemberExpression",
                            "start": 208,
                            "end": 228,
                            "loc": {
                              "start": {
                                "line": 9,
                                "column": 4
                              },
                              "end": {
                                "line": 9,
                                "column": 24
                              }
                            },
                            "object": {
                              "type": "Identifier",
                              "start": 208,
                              "end": 214,
                              "loc": {
                                "start": {
                                  "line": 9,
                                  "column": 4
                                },
                                "end": {
                                  "line": 9,
                                  "column": 10
                                },
                                "identifierName": "window"
                              },
                              "name": "window"
                            },
                            "property": {
                              "type": "Identifier",
                              "start": 215,
                              "end": 228,
                              "loc": {
                                "start": {
                                  "line": 9,
                                  "column": 11
                                },
                                "end": {
                                  "line": 9,
                                  "column": 24
                                },
                                "identifierName": "dispatchEvent"
                              },
                              "name": "dispatchEvent"
                            },
                            "computed": false
                          },
                          "arguments": [
                            {
                              "type": "Identifier",
                              "start": 229,
                              "end": 234,
                              "loc": {
                                "start": {
                                  "line": 9,
                                  "column": 25
                                },
                                "end": {
                                  "line": 9,
                                  "column": 30
                                },
                                "identifierName": "event"
                              },
                              "name": "event"
                            }
                          ]
                        }
                      },
                      {
                        "type": "ReturnStatement",
                        "start": 241,
                        "end": 261,
                        "loc": {
                          "start": {
                            "line": 10,
                            "column": 4
                          },
                          "end": {
                            "line": 10,
                            "column": 24
                          }
                        },
                        "argument": {
                          "type": "CallExpression",
                          "start": 248,
                          "end": 260,
                          "loc": {
                            "start": {
                              "line": 10,
                              "column": 11
                            },
                            "end": {
                              "line": 10,
                              "column": 23
                            }
                          },
                          "callee": {
                            "type": "Identifier",
                            "start": 248,
                            "end": 252,
                            "loc": {
                              "start": {
                                "line": 10,
                                "column": 11
                              },
                              "end": {
                                "line": 10,
                                "column": 15
                              },
                              "identifierName": "next"
                            },
                            "name": "next"
                          },
                          "arguments": [
                            {
                              "type": "Identifier",
                              "start": 253,
                              "end": 259,
                              "loc": {
                                "start": {
                                  "line": 10,
                                  "column": 16
                                },
                                "end": {
                                  "line": 10,
                                  "column": 22
                                },
                                "identifierName": "action"
                              },
                              "name": "action"
                            }
                          ]
                        }
                      }
                    ],
                    "directives": []
                  }
                }
              }
            },
            "leadingComments": null
          }
        ],
        "kind": "const",
        "leadingComments": [],
        "name": "_",
        "trailingComments": []
      },
      {
        "type": "Identifier",
        "start": 266,
        "end": 304,
        "loc": {
          "start": {
            "line": 13,
            "column": 0
          },
          "end": {
            "line": 13,
            "column": 38
          }
        },
        "declaration": {
          "type": "Identifier",
          "start": 281,
          "end": 303,
          "loc": {
            "start": {
              "line": 13,
              "column": 15
            },
            "end": {
              "line": 13,
              "column": 37
            },
            "identifierName": "eventEmitterMiddleware"
          },
          "name": "eventEmitterMiddleware"
        },
        "name": "_",
        "leadingComments": [],
        "trailingComments": []
      },
      {
        "type": "ExportDefaultDeclaration",
        "start": 266,
        "end": 304,
        "loc": {
          "start": {
            "line": 13,
            "column": 0
          },
          "end": {
            "line": 13,
            "column": 38
          }
        },
        "declaration": {
          "type": "VariableDeclaration",
          "start": 13,
          "end": 264,
          "loc": {
            "start": {
              "line": 2,
              "column": 0
            },
            "end": {
              "line": 11,
              "column": 2
            }
          },
          "declarations": [
            {
              "type": "VariableDeclarator",
              "start": 19,
              "end": 263,
              "loc": {
                "start": {
                  "line": 2,
                  "column": 6
                },
                "end": {
                  "line": 11,
                  "column": 1
                }
              },
              "id": {
                "type": "Identifier",
                "start": 19,
                "end": 41,
                "loc": {
                  "start": {
                    "line": 2,
                    "column": 6
                  },
                  "end": {
                    "line": 2,
                    "column": 28
                  },
                  "identifierName": "eventEmitterMiddleware"
                },
                "name": "eventEmitterMiddleware",
                "leadingComments": null
              },
              "init": {
                "type": "ArrowFunctionExpression",
                "start": 44,
                "end": 263,
                "loc": {
                  "start": {
                    "line": 2,
                    "column": 31
                  },
                  "end": {
                    "line": 11,
                    "column": 1
                  }
                },
                "id": {
                  "type": "Identifier",
                  "start": 19,
                  "end": 41,
                  "loc": {
                    "start": {
                      "line": 2,
                      "column": 6
                    },
                    "end": {
                      "line": 2,
                      "column": 28
                    },
                    "identifierName": "eventEmitterMiddleware"
                  },
                  "name": "eventEmitterMiddleware",
                  "leadingComments": null
                },
                "generator": false,
                "expression": true,
                "async": false,
                "params": [
                  {
                    "type": "Identifier",
                    "start": 44,
                    "end": 49,
                    "loc": {
                      "start": {
                        "line": 2,
                        "column": 31
                      },
                      "end": {
                        "line": 2,
                        "column": 36
                      },
                      "identifierName": "store"
                    },
                    "name": "store"
                  }
                ],
                "body": {
                  "type": "ArrowFunctionExpression",
                  "start": 53,
                  "end": 263,
                  "loc": {
                    "start": {
                      "line": 2,
                      "column": 40
                    },
                    "end": {
                      "line": 11,
                      "column": 1
                    }
                  },
                  "id": null,
                  "generator": false,
                  "expression": true,
                  "async": false,
                  "params": [
                    {
                      "type": "Identifier",
                      "start": 53,
                      "end": 57,
                      "loc": {
                        "start": {
                          "line": 2,
                          "column": 40
                        },
                        "end": {
                          "line": 2,
                          "column": 44
                        },
                        "identifierName": "next"
                      },
                      "name": "next"
                    }
                  ],
                  "body": {
                    "type": "ArrowFunctionExpression",
                    "start": 61,
                    "end": 263,
                    "loc": {
                      "start": {
                        "line": 2,
                        "column": 48
                      },
                      "end": {
                        "line": 11,
                        "column": 1
                      }
                    },
                    "id": null,
                    "generator": false,
                    "expression": false,
                    "async": false,
                    "params": [
                      {
                        "type": "Identifier",
                        "start": 61,
                        "end": 67,
                        "loc": {
                          "start": {
                            "line": 2,
                            "column": 48
                          },
                          "end": {
                            "line": 2,
                            "column": 54
                          },
                          "identifierName": "action"
                        },
                        "name": "action"
                      }
                    ],
                    "body": {
                      "type": "BlockStatement",
                      "start": 71,
                      "end": 263,
                      "loc": {
                        "start": {
                          "line": 2,
                          "column": 58
                        },
                        "end": {
                          "line": 11,
                          "column": 1
                        }
                      },
                      "body": [
                        {
                          "type": "VariableDeclaration",
                          "start": 77,
                          "end": 202,
                          "loc": {
                            "start": {
                              "line": 3,
                              "column": 4
                            },
                            "end": {
                              "line": 7,
                              "column": 7
                            }
                          },
                          "declarations": [
                            {
                              "type": "VariableDeclarator",
                              "start": 83,
                              "end": 201,
                              "loc": {
                                "start": {
                                  "line": 3,
                                  "column": 10
                                },
                                "end": {
                                  "line": 7,
                                  "column": 6
                                }
                              },
                              "id": {
                                "type": "Identifier",
                                "start": 83,
                                "end": 88,
                                "loc": {
                                  "start": {
                                    "line": 3,
                                    "column": 10
                                  },
                                  "end": {
                                    "line": 3,
                                    "column": 15
                                  },
                                  "identifierName": "event"
                                },
                                "name": "event"
                              },
                              "init": {
                                "type": "NewExpression",
                                "start": 91,
                                "end": 201,
                                "loc": {
                                  "start": {
                                    "line": 3,
                                    "column": 18
                                  },
                                  "end": {
                                    "line": 7,
                                    "column": 6
                                  }
                                },
                                "callee": {
                                  "type": "Identifier",
                                  "start": 95,
                                  "end": 106,
                                  "loc": {
                                    "start": {
                                      "line": 3,
                                      "column": 22
                                    },
                                    "end": {
                                      "line": 3,
                                      "column": 33
                                    },
                                    "identifierName": "CustomEvent"
                                  },
                                  "name": "CustomEvent"
                                },
                                "arguments": [
                                  {
                                    "type": "TemplateLiteral",
                                    "start": 107,
                                    "end": 127,
                                    "loc": {
                                      "start": {
                                        "line": 3,
                                        "column": 34
                                      },
                                      "end": {
                                        "line": 3,
                                        "column": 54
                                      }
                                    },
                                    "expressions": [
                                      {
                                        "type": "MemberExpression",
                                        "start": 114,
                                        "end": 125,
                                        "loc": {
                                          "start": {
                                            "line": 3,
                                            "column": 41
                                          },
                                          "end": {
                                            "line": 3,
                                            "column": 52
                                          }
                                        },
                                        "object": {
                                          "type": "Identifier",
                                          "start": 114,
                                          "end": 120,
                                          "loc": {
                                            "start": {
                                              "line": 3,
                                              "column": 41
                                            },
                                            "end": {
                                              "line": 3,
                                              "column": 47
                                            },
                                            "identifierName": "action"
                                          },
                                          "name": "action"
                                        },
                                        "property": {
                                          "type": "Identifier",
                                          "start": 121,
                                          "end": 125,
                                          "loc": {
                                            "start": {
                                              "line": 3,
                                              "column": 48
                                            },
                                            "end": {
                                              "line": 3,
                                              "column": 52
                                            },
                                            "identifierName": "type"
                                          },
                                          "name": "type"
                                        },
                                        "computed": false
                                      }
                                    ],
                                    "quasis": [
                                      {
                                        "type": "TemplateElement",
                                        "start": 108,
                                        "end": 112,
                                        "loc": {
                                          "start": {
                                            "line": 3,
                                            "column": 35
                                          },
                                          "end": {
                                            "line": 3,
                                            "column": 39
                                          }
                                        },
                                        "value": {
                                          "raw": "rwc-",
                                          "cooked": "rwc-"
                                        },
                                        "tail": false
                                      },
                                      {
                                        "type": "TemplateElement",
                                        "start": 126,
                                        "end": 126,
                                        "loc": {
                                          "start": {
                                            "line": 3,
                                            "column": 53
                                          },
                                          "end": {
                                            "line": 3,
                                            "column": 53
                                          }
                                        },
                                        "value": {
                                          "raw": "",
                                          "cooked": ""
                                        },
                                        "tail": true
                                      }
                                    ]
                                  },
                                  {
                                    "type": "ObjectExpression",
                                    "start": 129,
                                    "end": 200,
                                    "loc": {
                                      "start": {
                                        "line": 3,
                                        "column": 56
                                      },
                                      "end": {
                                        "line": 7,
                                        "column": 5
                                      }
                                    },
                                    "properties": [
                                      {
                                        "type": "ObjectProperty",
                                        "start": 139,
                                        "end": 194,
                                        "loc": {
                                          "start": {
                                            "line": 4,
                                            "column": 8
                                          },
                                          "end": {
                                            "line": 6,
                                            "column": 9
                                          }
                                        },
                                        "method": false,
                                        "shorthand": false,
                                        "computed": false,
                                        "key": {
                                          "type": "Identifier",
                                          "start": 139,
                                          "end": 145,
                                          "loc": {
                                            "start": {
                                              "line": 4,
                                              "column": 8
                                            },
                                            "end": {
                                              "line": 4,
                                              "column": 14
                                            },
                                            "identifierName": "detail"
                                          },
                                          "name": "detail"
                                        },
                                        "value": {
                                          "type": "ObjectExpression",
                                          "start": 147,
                                          "end": 194,
                                          "loc": {
                                            "start": {
                                              "line": 4,
                                              "column": 16
                                            },
                                            "end": {
                                              "line": 6,
                                              "column": 9
                                            }
                                          },
                                          "properties": [
                                            {
                                              "type": "ObjectProperty",
                                              "start": 161,
                                              "end": 184,
                                              "loc": {
                                                "start": {
                                                  "line": 5,
                                                  "column": 12
                                                },
                                                "end": {
                                                  "line": 5,
                                                  "column": 35
                                                }
                                              },
                                              "method": false,
                                              "shorthand": false,
                                              "computed": false,
                                              "key": {
                                                "type": "Identifier",
                                                "start": 161,
                                                "end": 168,
                                                "loc": {
                                                  "start": {
                                                    "line": 5,
                                                    "column": 12
                                                  },
                                                  "end": {
                                                    "line": 5,
                                                    "column": 19
                                                  },
                                                  "identifierName": "payload"
                                                },
                                                "name": "payload"
                                              },
                                              "value": {
                                                "type": "MemberExpression",
                                                "start": 170,
                                                "end": 184,
                                                "loc": {
                                                  "start": {
                                                    "line": 5,
                                                    "column": 21
                                                  },
                                                  "end": {
                                                    "line": 5,
                                                    "column": 35
                                                  }
                                                },
                                                "object": {
                                                  "type": "Identifier",
                                                  "start": 170,
                                                  "end": 176,
                                                  "loc": {
                                                    "start": {
                                                      "line": 5,
                                                      "column": 21
                                                    },
                                                    "end": {
                                                      "line": 5,
                                                      "column": 27
                                                    },
                                                    "identifierName": "action"
                                                  },
                                                  "name": "action"
                                                },
                                                "property": {
                                                  "type": "Identifier",
                                                  "start": 177,
                                                  "end": 184,
                                                  "loc": {
                                                    "start": {
                                                      "line": 5,
                                                      "column": 28
                                                    },
                                                    "end": {
                                                      "line": 5,
                                                      "column": 35
                                                    },
                                                    "identifierName": "payload"
                                                  },
                                                  "name": "payload"
                                                },
                                                "computed": false
                                              }
                                            }
                                          ]
                                        }
                                      }
                                    ]
                                  }
                                ]
                              }
                            }
                          ],
                          "kind": "const"
                        },
                        {
                          "type": "ExpressionStatement",
                          "start": 208,
                          "end": 236,
                          "loc": {
                            "start": {
                              "line": 9,
                              "column": 4
                            },
                            "end": {
                              "line": 9,
                              "column": 32
                            }
                          },
                          "expression": {
                            "type": "CallExpression",
                            "start": 208,
                            "end": 235,
                            "loc": {
                              "start": {
                                "line": 9,
                                "column": 4
                              },
                              "end": {
                                "line": 9,
                                "column": 31
                              }
                            },
                            "callee": {
                              "type": "MemberExpression",
                              "start": 208,
                              "end": 228,
                              "loc": {
                                "start": {
                                  "line": 9,
                                  "column": 4
                                },
                                "end": {
                                  "line": 9,
                                  "column": 24
                                }
                              },
                              "object": {
                                "type": "Identifier",
                                "start": 208,
                                "end": 214,
                                "loc": {
                                  "start": {
                                    "line": 9,
                                    "column": 4
                                  },
                                  "end": {
                                    "line": 9,
                                    "column": 10
                                  },
                                  "identifierName": "window"
                                },
                                "name": "window"
                              },
                              "property": {
                                "type": "Identifier",
                                "start": 215,
                                "end": 228,
                                "loc": {
                                  "start": {
                                    "line": 9,
                                    "column": 11
                                  },
                                  "end": {
                                    "line": 9,
                                    "column": 24
                                  },
                                  "identifierName": "dispatchEvent"
                                },
                                "name": "dispatchEvent"
                              },
                              "computed": false
                            },
                            "arguments": [
                              {
                                "type": "Identifier",
                                "start": 229,
                                "end": 234,
                                "loc": {
                                  "start": {
                                    "line": 9,
                                    "column": 25
                                  },
                                  "end": {
                                    "line": 9,
                                    "column": 30
                                  },
                                  "identifierName": "event"
                                },
                                "name": "event"
                              }
                            ]
                          }
                        },
                        {
                          "type": "ReturnStatement",
                          "start": 241,
                          "end": 261,
                          "loc": {
                            "start": {
                              "line": 10,
                              "column": 4
                            },
                            "end": {
                              "line": 10,
                              "column": 24
                            }
                          },
                          "argument": {
                            "type": "CallExpression",
                            "start": 248,
                            "end": 260,
                            "loc": {
                              "start": {
                                "line": 10,
                                "column": 11
                              },
                              "end": {
                                "line": 10,
                                "column": 23
                              }
                            },
                            "callee": {
                              "type": "Identifier",
                              "start": 248,
                              "end": 252,
                              "loc": {
                                "start": {
                                  "line": 10,
                                  "column": 11
                                },
                                "end": {
                                  "line": 10,
                                  "column": 15
                                },
                                "identifierName": "next"
                              },
                              "name": "next"
                            },
                            "arguments": [
                              {
                                "type": "Identifier",
                                "start": 253,
                                "end": 259,
                                "loc": {
                                  "start": {
                                    "line": 10,
                                    "column": 16
                                  },
                                  "end": {
                                    "line": 10,
                                    "column": 22
                                  },
                                  "identifierName": "action"
                                },
                                "name": "action"
                              }
                            ]
                          }
                        }
                      ],
                      "directives": []
                    }
                  }
                }
              },
              "leadingComments": null
            }
          ],
          "kind": "const",
          "leadingComments": [
            {
              "type": "CommentLine",
              "value": " @ts-check",
              "start": 0,
              "end": 12,
              "loc": {
                "start": {
                  "line": 1,
                  "column": 0
                },
                "end": {
                  "line": 1,
                  "column": 12
                }
              }
            }
          ],
          "trailingComments": []
        }
      }
    ],
    "directives": []
  },
  "comments": [
    {
      "type": "CommentLine",
      "value": " @ts-check",
      "start": 0,
      "end": 12,
      "loc": {
        "start": {
          "line": 1,
          "column": 0
        },
        "end": {
          "line": 1,
          "column": 12
        }
      }
    }
  ],
  "tokens": [
    {
      "type": "CommentLine",
      "value": " @ts-check",
      "start": 0,
      "end": 12,
      "loc": {
        "start": {
          "line": 1,
          "column": 0
        },
        "end": {
          "line": 1,
          "column": 12
        }
      }
    },
    {
      "type": {
        "label": "const",
        "keyword": "const",
        "beforeExpr": false,
        "startsExpr": false,
        "rightAssociative": false,
        "isLoop": false,
        "isAssign": false,
        "prefix": false,
        "postfix": false,
        "binop": null,
        "updateContext": null
      },
      "value": "const",
      "start": 13,
      "end": 18,
      "loc": {
        "start": {
          "line": 2,
          "column": 0
        },
        "end": {
          "line": 2,
          "column": 5
        }
      }
    },
    {
      "type": {
        "label": "name",
        "beforeExpr": false,
        "startsExpr": true,
        "rightAssociative": false,
        "isLoop": false,
        "isAssign": false,
        "prefix": false,
        "postfix": false,
        "binop": null
      },
      "value": "eventEmitterMiddleware",
      "start": 19,
      "end": 41,
      "loc": {
        "start": {
          "line": 2,
          "column": 6
        },
        "end": {
          "line": 2,
          "column": 28
        }
      }
    },
    {
      "type": {
        "label": "=",
        "beforeExpr": true,
        "startsExpr": false,
        "rightAssociative": false,
        "isLoop": false,
        "isAssign": true,
        "prefix": false,
        "postfix": false,
        "binop": null,
        "updateContext": null
      },
      "value": "=",
      "start": 42,
      "end": 43,
      "loc": {
        "start": {
          "line": 2,
          "column": 29
        },
        "end": {
          "line": 2,
          "column": 30
        }
      }
    },
    {
      "type": {
        "label": "name",
        "beforeExpr": false,
        "startsExpr": true,
        "rightAssociative": false,
        "isLoop": false,
        "isAssign": false,
        "prefix": false,
        "postfix": false,
        "binop": null
      },
      "value": "store",
      "start": 44,
      "end": 49,
      "loc": {
        "start": {
          "line": 2,
          "column": 31
        },
        "end": {
          "line": 2,
          "column": 36
        }
      }
    },
    {
      "type": {
        "label": "=>",
        "beforeExpr": true,
        "startsExpr": false,
        "rightAssociative": false,
        "isLoop": false,
        "isAssign": false,
        "prefix": false,
        "postfix": false,
        "binop": null,
        "updateContext": null
      },
      "start": 50,
      "end": 52,
      "loc": {
        "start": {
          "line": 2,
          "column": 37
        },
        "end": {
          "line": 2,
          "column": 39
        }
      }
    },
    {
      "type": {
        "label": "name",
        "beforeExpr": false,
        "startsExpr": true,
        "rightAssociative": false,
        "isLoop": false,
        "isAssign": false,
        "prefix": false,
        "postfix": false,
        "binop": null
      },
      "value": "next",
      "start": 53,
      "end": 57,
      "loc": {
        "start": {
          "line": 2,
          "column": 40
        },
        "end": {
          "line": 2,
          "column": 44
        }
      }
    },
    {
      "type": {
        "label": "=>",
        "beforeExpr": true,
        "startsExpr": false,
        "rightAssociative": false,
        "isLoop": false,
        "isAssign": false,
        "prefix": false,
        "postfix": false,
        "binop": null,
        "updateContext": null
      },
      "start": 58,
      "end": 60,
      "loc": {
        "start": {
          "line": 2,
          "column": 45
        },
        "end": {
          "line": 2,
          "column": 47
        }
      }
    },
    {
      "type": {
        "label": "name",
        "beforeExpr": false,
        "startsExpr": true,
        "rightAssociative": false,
        "isLoop": false,
        "isAssign": false,
        "prefix": false,
        "postfix": false,
        "binop": null
      },
      "value": "action",
      "start": 61,
      "end": 67,
      "loc": {
        "start": {
          "line": 2,
          "column": 48
        },
        "end": {
          "line": 2,
          "column": 54
        }
      }
    },
    {
      "type": {
        "label": "=>",
        "beforeExpr": true,
        "startsExpr": false,
        "rightAssociative": false,
        "isLoop": false,
        "isAssign": false,
        "prefix": false,
        "postfix": false,
        "binop": null,
        "updateContext": null
      },
      "start": 68,
      "end": 70,
      "loc": {
        "start": {
          "line": 2,
          "column": 55
        },
        "end": {
          "line": 2,
          "column": 57
        }
      }
    },
    {
      "type": {
        "label": "{",
        "beforeExpr": true,
        "startsExpr": true,
        "rightAssociative": false,
        "isLoop": false,
        "isAssign": false,
        "prefix": false,
        "postfix": false,
        "binop": null
      },
      "start": 71,
      "end": 72,
      "loc": {
        "start": {
          "line": 2,
          "column": 58
        },
        "end": {
          "line": 2,
          "column": 59
        }
      }
    },
    {
      "type": {
        "label": "const",
        "keyword": "const",
        "beforeExpr": false,
        "startsExpr": false,
        "rightAssociative": false,
        "isLoop": false,
        "isAssign": false,
        "prefix": false,
        "postfix": false,
        "binop": null,
        "updateContext": null
      },
      "value": "const",
      "start": 77,
      "end": 82,
      "loc": {
        "start": {
          "line": 3,
          "column": 4
        },
        "end": {
          "line": 3,
          "column": 9
        }
      }
    },
    {
      "type": {
        "label": "name",
        "beforeExpr": false,
        "startsExpr": true,
        "rightAssociative": false,
        "isLoop": false,
        "isAssign": false,
        "prefix": false,
        "postfix": false,
        "binop": null
      },
      "value": "event",
      "start": 83,
      "end": 88,
      "loc": {
        "start": {
          "line": 3,
          "column": 10
        },
        "end": {
          "line": 3,
          "column": 15
        }
      }
    },
    {
      "type": {
        "label": "=",
        "beforeExpr": true,
        "startsExpr": false,
        "rightAssociative": false,
        "isLoop": false,
        "isAssign": true,
        "prefix": false,
        "postfix": false,
        "binop": null,
        "updateContext": null
      },
      "value": "=",
      "start": 89,
      "end": 90,
      "loc": {
        "start": {
          "line": 3,
          "column": 16
        },
        "end": {
          "line": 3,
          "column": 17
        }
      }
    },
    {
      "type": {
        "label": "new",
        "keyword": "new",
        "beforeExpr": true,
        "startsExpr": true,
        "rightAssociative": false,
        "isLoop": false,
        "isAssign": false,
        "prefix": false,
        "postfix": false,
        "binop": null,
        "updateContext": null
      },
      "value": "new",
      "start": 91,
      "end": 94,
      "loc": {
        "start": {
          "line": 3,
          "column": 18
        },
        "end": {
          "line": 3,
          "column": 21
        }
      }
    },
    {
      "type": {
        "label": "name",
        "beforeExpr": false,
        "startsExpr": true,
        "rightAssociative": false,
        "isLoop": false,
        "isAssign": false,
        "prefix": false,
        "postfix": false,
        "binop": null
      },
      "value": "CustomEvent",
      "start": 95,
      "end": 106,
      "loc": {
        "start": {
          "line": 3,
          "column": 22
        },
        "end": {
          "line": 3,
          "column": 33
        }
      }
    },
    {
      "type": {
        "label": "(",
        "beforeExpr": true,
        "startsExpr": true,
        "rightAssociative": false,
        "isLoop": false,
        "isAssign": false,
        "prefix": false,
        "postfix": false,
        "binop": null
      },
      "start": 106,
      "end": 107,
      "loc": {
        "start": {
          "line": 3,
          "column": 33
        },
        "end": {
          "line": 3,
          "column": 34
        }
      }
    },
    {
      "type": {
        "label": "`",
        "beforeExpr": false,
        "startsExpr": true,
        "rightAssociative": false,
        "isLoop": false,
        "isAssign": false,
        "prefix": false,
        "postfix": false,
        "binop": null
      },
      "start": 107,
      "end": 108,
      "loc": {
        "start": {
          "line": 3,
          "column": 34
        },
        "end": {
          "line": 3,
          "column": 35
        }
      }
    },
    {
      "type": {
        "label": "template",
        "beforeExpr": false,
        "startsExpr": false,
        "rightAssociative": false,
        "isLoop": false,
        "isAssign": false,
        "prefix": false,
        "postfix": false,
        "binop": null,
        "updateContext": null
      },
      "value": "rwc-",
      "start": 108,
      "end": 112,
      "loc": {
        "start": {
          "line": 3,
          "column": 35
        },
        "end": {
          "line": 3,
          "column": 39
        }
      }
    },
    {
      "type": {
        "label": "${",
        "beforeExpr": true,
        "startsExpr": true,
        "rightAssociative": false,
        "isLoop": false,
        "isAssign": false,
        "prefix": false,
        "postfix": false,
        "binop": null
      },
      "start": 112,
      "end": 114,
      "loc": {
        "start": {
          "line": 3,
          "column": 39
        },
        "end": {
          "line": 3,
          "column": 41
        }
      }
    },
    {
      "type": {
        "label": "name",
        "beforeExpr": false,
        "startsExpr": true,
        "rightAssociative": false,
        "isLoop": false,
        "isAssign": false,
        "prefix": false,
        "postfix": false,
        "binop": null
      },
      "value": "action",
      "start": 114,
      "end": 120,
      "loc": {
        "start": {
          "line": 3,
          "column": 41
        },
        "end": {
          "line": 3,
          "column": 47
        }
      }
    },
    {
      "type": {
        "label": ".",
        "beforeExpr": false,
        "startsExpr": false,
        "rightAssociative": false,
        "isLoop": false,
        "isAssign": false,
        "prefix": false,
        "postfix": false,
        "binop": null,
        "updateContext": null
      },
      "start": 120,
      "end": 121,
      "loc": {
        "start": {
          "line": 3,
          "column": 47
        },
        "end": {
          "line": 3,
          "column": 48
        }
      }
    },
    {
      "type": {
        "label": "name",
        "beforeExpr": false,
        "startsExpr": true,
        "rightAssociative": false,
        "isLoop": false,
        "isAssign": false,
        "prefix": false,
        "postfix": false,
        "binop": null
      },
      "value": "type",
      "start": 121,
      "end": 125,
      "loc": {
        "start": {
          "line": 3,
          "column": 48
        },
        "end": {
          "line": 3,
          "column": 52
        }
      }
    },
    {
      "type": {
        "label": "}",
        "beforeExpr": false,
        "startsExpr": false,
        "rightAssociative": false,
        "isLoop": false,
        "isAssign": false,
        "prefix": false,
        "postfix": false,
        "binop": null
      },
      "start": 125,
      "end": 126,
      "loc": {
        "start": {
          "line": 3,
          "column": 52
        },
        "end": {
          "line": 3,
          "column": 53
        }
      }
    },
    {
      "type": {
        "label": "template",
        "beforeExpr": false,
        "startsExpr": false,
        "rightAssociative": false,
        "isLoop": false,
        "isAssign": false,
        "prefix": false,
        "postfix": false,
        "binop": null,
        "updateContext": null
      },
      "value": "",
      "start": 126,
      "end": 126,
      "loc": {
        "start": {
          "line": 3,
          "column": 53
        },
        "end": {
          "line": 3,
          "column": 53
        }
      }
    },
    {
      "type": {
        "label": "`",
        "beforeExpr": false,
        "startsExpr": true,
        "rightAssociative": false,
        "isLoop": false,
        "isAssign": false,
        "prefix": false,
        "postfix": false,
        "binop": null
      },
      "start": 126,
      "end": 127,
      "loc": {
        "start": {
          "line": 3,
          "column": 53
        },
        "end": {
          "line": 3,
          "column": 54
        }
      }
    },
    {
      "type": {
        "label": ",",
        "beforeExpr": true,
        "startsExpr": false,
        "rightAssociative": false,
        "isLoop": false,
        "isAssign": false,
        "prefix": false,
        "postfix": false,
        "binop": null,
        "updateContext": null
      },
      "start": 127,
      "end": 128,
      "loc": {
        "start": {
          "line": 3,
          "column": 54
        },
        "end": {
          "line": 3,
          "column": 55
        }
      }
    },
    {
      "type": {
        "label": "{",
        "beforeExpr": true,
        "startsExpr": true,
        "rightAssociative": false,
        "isLoop": false,
        "isAssign": false,
        "prefix": false,
        "postfix": false,
        "binop": null
      },
      "start": 129,
      "end": 130,
      "loc": {
        "start": {
          "line": 3,
          "column": 56
        },
        "end": {
          "line": 3,
          "column": 57
        }
      }
    },
    {
      "type": {
        "label": "name",
        "beforeExpr": false,
        "startsExpr": true,
        "rightAssociative": false,
        "isLoop": false,
        "isAssign": false,
        "prefix": false,
        "postfix": false,
        "binop": null
      },
      "value": "detail",
      "start": 139,
      "end": 145,
      "loc": {
        "start": {
          "line": 4,
          "column": 8
        },
        "end": {
          "line": 4,
          "column": 14
        }
      }
    },
    {
      "type": {
        "label": ":",
        "beforeExpr": true,
        "startsExpr": false,
        "rightAssociative": false,
        "isLoop": false,
        "isAssign": false,
        "prefix": false,
        "postfix": false,
        "binop": null,
        "updateContext": null
      },
      "start": 145,
      "end": 146,
      "loc": {
        "start": {
          "line": 4,
          "column": 14
        },
        "end": {
          "line": 4,
          "column": 15
        }
      }
    },
    {
      "type": {
        "label": "{",
        "beforeExpr": true,
        "startsExpr": true,
        "rightAssociative": false,
        "isLoop": false,
        "isAssign": false,
        "prefix": false,
        "postfix": false,
        "binop": null
      },
      "start": 147,
      "end": 148,
      "loc": {
        "start": {
          "line": 4,
          "column": 16
        },
        "end": {
          "line": 4,
          "column": 17
        }
      }
    },
    {
      "type": {
        "label": "name",
        "beforeExpr": false,
        "startsExpr": true,
        "rightAssociative": false,
        "isLoop": false,
        "isAssign": false,
        "prefix": false,
        "postfix": false,
        "binop": null
      },
      "value": "payload",
      "start": 161,
      "end": 168,
      "loc": {
        "start": {
          "line": 5,
          "column": 12
        },
        "end": {
          "line": 5,
          "column": 19
        }
      }
    },
    {
      "type": {
        "label": ":",
        "beforeExpr": true,
        "startsExpr": false,
        "rightAssociative": false,
        "isLoop": false,
        "isAssign": false,
        "prefix": false,
        "postfix": false,
        "binop": null,
        "updateContext": null
      },
      "start": 168,
      "end": 169,
      "loc": {
        "start": {
          "line": 5,
          "column": 19
        },
        "end": {
          "line": 5,
          "column": 20
        }
      }
    },
    {
      "type": {
        "label": "name",
        "beforeExpr": false,
        "startsExpr": true,
        "rightAssociative": false,
        "isLoop": false,
        "isAssign": false,
        "prefix": false,
        "postfix": false,
        "binop": null
      },
      "value": "action",
      "start": 170,
      "end": 176,
      "loc": {
        "start": {
          "line": 5,
          "column": 21
        },
        "end": {
          "line": 5,
          "column": 27
        }
      }
    },
    {
      "type": {
        "label": ".",
        "beforeExpr": false,
        "startsExpr": false,
        "rightAssociative": false,
        "isLoop": false,
        "isAssign": false,
        "prefix": false,
        "postfix": false,
        "binop": null,
        "updateContext": null
      },
      "start": 176,
      "end": 177,
      "loc": {
        "start": {
          "line": 5,
          "column": 27
        },
        "end": {
          "line": 5,
          "column": 28
        }
      }
    },
    {
      "type": {
        "label": "name",
        "beforeExpr": false,
        "startsExpr": true,
        "rightAssociative": false,
        "isLoop": false,
        "isAssign": false,
        "prefix": false,
        "postfix": false,
        "binop": null
      },
      "value": "payload",
      "start": 177,
      "end": 184,
      "loc": {
        "start": {
          "line": 5,
          "column": 28
        },
        "end": {
          "line": 5,
          "column": 35
        }
      }
    },
    {
      "type": {
        "label": "}",
        "beforeExpr": false,
        "startsExpr": false,
        "rightAssociative": false,
        "isLoop": false,
        "isAssign": false,
        "prefix": false,
        "postfix": false,
        "binop": null
      },
      "start": 193,
      "end": 194,
      "loc": {
        "start": {
          "line": 6,
          "column": 8
        },
        "end": {
          "line": 6,
          "column": 9
        }
      }
    },
    {
      "type": {
        "label": "}",
        "beforeExpr": false,
        "startsExpr": false,
        "rightAssociative": false,
        "isLoop": false,
        "isAssign": false,
        "prefix": false,
        "postfix": false,
        "binop": null
      },
      "start": 199,
      "end": 200,
      "loc": {
        "start": {
          "line": 7,
          "column": 4
        },
        "end": {
          "line": 7,
          "column": 5
        }
      }
    },
    {
      "type": {
        "label": ")",
        "beforeExpr": false,
        "startsExpr": false,
        "rightAssociative": false,
        "isLoop": false,
        "isAssign": false,
        "prefix": false,
        "postfix": false,
        "binop": null
      },
      "start": 200,
      "end": 201,
      "loc": {
        "start": {
          "line": 7,
          "column": 5
        },
        "end": {
          "line": 7,
          "column": 6
        }
      }
    },
    {
      "type": {
        "label": ";",
        "beforeExpr": true,
        "startsExpr": false,
        "rightAssociative": false,
        "isLoop": false,
        "isAssign": false,
        "prefix": false,
        "postfix": false,
        "binop": null,
        "updateContext": null
      },
      "start": 201,
      "end": 202,
      "loc": {
        "start": {
          "line": 7,
          "column": 6
        },
        "end": {
          "line": 7,
          "column": 7
        }
      }
    },
    {
      "type": {
        "label": "name",
        "beforeExpr": false,
        "startsExpr": true,
        "rightAssociative": false,
        "isLoop": false,
        "isAssign": false,
        "prefix": false,
        "postfix": false,
        "binop": null
      },
      "value": "window",
      "start": 208,
      "end": 214,
      "loc": {
        "start": {
          "line": 9,
          "column": 4
        },
        "end": {
          "line": 9,
          "column": 10
        }
      }
    },
    {
      "type": {
        "label": ".",
        "beforeExpr": false,
        "startsExpr": false,
        "rightAssociative": false,
        "isLoop": false,
        "isAssign": false,
        "prefix": false,
        "postfix": false,
        "binop": null,
        "updateContext": null
      },
      "start": 214,
      "end": 215,
      "loc": {
        "start": {
          "line": 9,
          "column": 10
        },
        "end": {
          "line": 9,
          "column": 11
        }
      }
    },
    {
      "type": {
        "label": "name",
        "beforeExpr": false,
        "startsExpr": true,
        "rightAssociative": false,
        "isLoop": false,
        "isAssign": false,
        "prefix": false,
        "postfix": false,
        "binop": null
      },
      "value": "dispatchEvent",
      "start": 215,
      "end": 228,
      "loc": {
        "start": {
          "line": 9,
          "column": 11
        },
        "end": {
          "line": 9,
          "column": 24
        }
      }
    },
    {
      "type": {
        "label": "(",
        "beforeExpr": true,
        "startsExpr": true,
        "rightAssociative": false,
        "isLoop": false,
        "isAssign": false,
        "prefix": false,
        "postfix": false,
        "binop": null
      },
      "start": 228,
      "end": 229,
      "loc": {
        "start": {
          "line": 9,
          "column": 24
        },
        "end": {
          "line": 9,
          "column": 25
        }
      }
    },
    {
      "type": {
        "label": "name",
        "beforeExpr": false,
        "startsExpr": true,
        "rightAssociative": false,
        "isLoop": false,
        "isAssign": false,
        "prefix": false,
        "postfix": false,
        "binop": null
      },
      "value": "event",
      "start": 229,
      "end": 234,
      "loc": {
        "start": {
          "line": 9,
          "column": 25
        },
        "end": {
          "line": 9,
          "column": 30
        }
      }
    },
    {
      "type": {
        "label": ")",
        "beforeExpr": false,
        "startsExpr": false,
        "rightAssociative": false,
        "isLoop": false,
        "isAssign": false,
        "prefix": false,
        "postfix": false,
        "binop": null
      },
      "start": 234,
      "end": 235,
      "loc": {
        "start": {
          "line": 9,
          "column": 30
        },
        "end": {
          "line": 9,
          "column": 31
        }
      }
    },
    {
      "type": {
        "label": ";",
        "beforeExpr": true,
        "startsExpr": false,
        "rightAssociative": false,
        "isLoop": false,
        "isAssign": false,
        "prefix": false,
        "postfix": false,
        "binop": null,
        "updateContext": null
      },
      "start": 235,
      "end": 236,
      "loc": {
        "start": {
          "line": 9,
          "column": 31
        },
        "end": {
          "line": 9,
          "column": 32
        }
      }
    },
    {
      "type": {
        "label": "return",
        "keyword": "return",
        "beforeExpr": true,
        "startsExpr": false,
        "rightAssociative": false,
        "isLoop": false,
        "isAssign": false,
        "prefix": false,
        "postfix": false,
        "binop": null,
        "updateContext": null
      },
      "value": "return",
      "start": 241,
      "end": 247,
      "loc": {
        "start": {
          "line": 10,
          "column": 4
        },
        "end": {
          "line": 10,
          "column": 10
        }
      }
    },
    {
      "type": {
        "label": "name",
        "beforeExpr": false,
        "startsExpr": true,
        "rightAssociative": false,
        "isLoop": false,
        "isAssign": false,
        "prefix": false,
        "postfix": false,
        "binop": null
      },
      "value": "next",
      "start": 248,
      "end": 252,
      "loc": {
        "start": {
          "line": 10,
          "column": 11
        },
        "end": {
          "line": 10,
          "column": 15
        }
      }
    },
    {
      "type": {
        "label": "(",
        "beforeExpr": true,
        "startsExpr": true,
        "rightAssociative": false,
        "isLoop": false,
        "isAssign": false,
        "prefix": false,
        "postfix": false,
        "binop": null
      },
      "start": 252,
      "end": 253,
      "loc": {
        "start": {
          "line": 10,
          "column": 15
        },
        "end": {
          "line": 10,
          "column": 16
        }
      }
    },
    {
      "type": {
        "label": "name",
        "beforeExpr": false,
        "startsExpr": true,
        "rightAssociative": false,
        "isLoop": false,
        "isAssign": false,
        "prefix": false,
        "postfix": false,
        "binop": null
      },
      "value": "action",
      "start": 253,
      "end": 259,
      "loc": {
        "start": {
          "line": 10,
          "column": 16
        },
        "end": {
          "line": 10,
          "column": 22
        }
      }
    },
    {
      "type": {
        "label": ")",
        "beforeExpr": false,
        "startsExpr": false,
        "rightAssociative": false,
        "isLoop": false,
        "isAssign": false,
        "prefix": false,
        "postfix": false,
        "binop": null
      },
      "start": 259,
      "end": 260,
      "loc": {
        "start": {
          "line": 10,
          "column": 22
        },
        "end": {
          "line": 10,
          "column": 23
        }
      }
    },
    {
      "type": {
        "label": ";",
        "beforeExpr": true,
        "startsExpr": false,
        "rightAssociative": false,
        "isLoop": false,
        "isAssign": false,
        "prefix": false,
        "postfix": false,
        "binop": null,
        "updateContext": null
      },
      "start": 260,
      "end": 261,
      "loc": {
        "start": {
          "line": 10,
          "column": 23
        },
        "end": {
          "line": 10,
          "column": 24
        }
      }
    },
    {
      "type": {
        "label": "}",
        "beforeExpr": false,
        "startsExpr": false,
        "rightAssociative": false,
        "isLoop": false,
        "isAssign": false,
        "prefix": false,
        "postfix": false,
        "binop": null
      },
      "start": 262,
      "end": 263,
      "loc": {
        "start": {
          "line": 11,
          "column": 0
        },
        "end": {
          "line": 11,
          "column": 1
        }
      }
    },
    {
      "type": {
        "label": ";",
        "beforeExpr": true,
        "startsExpr": false,
        "rightAssociative": false,
        "isLoop": false,
        "isAssign": false,
        "prefix": false,
        "postfix": false,
        "binop": null,
        "updateContext": null
      },
      "start": 263,
      "end": 264,
      "loc": {
        "start": {
          "line": 11,
          "column": 1
        },
        "end": {
          "line": 11,
          "column": 2
        }
      }
    },
    {
      "type": {
        "label": "export",
        "keyword": "export",
        "beforeExpr": false,
        "startsExpr": false,
        "rightAssociative": false,
        "isLoop": false,
        "isAssign": false,
        "prefix": false,
        "postfix": false,
        "binop": null,
        "updateContext": null
      },
      "value": "export",
      "start": 266,
      "end": 272,
      "loc": {
        "start": {
          "line": 13,
          "column": 0
        },
        "end": {
          "line": 13,
          "column": 6
        }
      }
    },
    {
      "type": {
        "label": "default",
        "keyword": "default",
        "beforeExpr": true,
        "startsExpr": false,
        "rightAssociative": false,
        "isLoop": false,
        "isAssign": false,
        "prefix": false,
        "postfix": false,
        "binop": null,
        "updateContext": null
      },
      "value": "default",
      "start": 273,
      "end": 280,
      "loc": {
        "start": {
          "line": 13,
          "column": 7
        },
        "end": {
          "line": 13,
          "column": 14
        }
      }
    },
    {
      "type": {
        "label": "name",
        "beforeExpr": false,
        "startsExpr": true,
        "rightAssociative": false,
        "isLoop": false,
        "isAssign": false,
        "prefix": false,
        "postfix": false,
        "binop": null
      },
      "value": "eventEmitterMiddleware",
      "start": 281,
      "end": 303,
      "loc": {
        "start": {
          "line": 13,
          "column": 15
        },
        "end": {
          "line": 13,
          "column": 37
        }
      }
    },
    {
      "type": {
        "label": ";",
        "beforeExpr": true,
        "startsExpr": false,
        "rightAssociative": false,
        "isLoop": false,
        "isAssign": false,
        "prefix": false,
        "postfix": false,
        "binop": null,
        "updateContext": null
      },
      "start": 303,
      "end": 304,
      "loc": {
        "start": {
          "line": 13,
          "column": 37
        },
        "end": {
          "line": 13,
          "column": 38
        }
      }
    },
    {
      "type": {
        "label": "eof",
        "beforeExpr": false,
        "startsExpr": false,
        "rightAssociative": false,
        "isLoop": false,
        "isAssign": false,
        "prefix": false,
        "postfix": false,
        "binop": null,
        "updateContext": null
      },
      "start": 305,
      "end": 305,
      "loc": {
        "start": {
          "line": 14,
          "column": 0
        },
        "end": {
          "line": 14,
          "column": 0
        }
      }
    }
  ]
}